docker_detector/__init__.py
docker_detector/core.py
docker_detector/py.typed
docker_detector-1.0.1.dist-info/METADATA
docker_detector-1.0.1.dist-info/WHEEL
docker_detector-1.0.1.dist-info/licenses/LICENSE
docker_detector-1.0.1.dist-info/RECORD
