Metadata-Version: 2.4
Name: docker-detector
Version: 1.0.1
Summary: Detect if your Python process is running inside a Docker container. Inspired by the popular is-docker npm package. Supports cached results with optional refresh.
Project-URL: Homepage, https://github.com/ysskrishna/docker-detector
Project-URL: Repository, https://github.com/ysskrishna/docker-detector.git
Project-URL: Issues, https://github.com/ysskrishna/docker-detector/issues
Project-URL: Changelog, https://github.com/ysskrishna/docker-detector/blob/main/CHANGELOG.md
Project-URL: Discussions, https://github.com/ysskrishna/docker-detector/discussions
Author-email: "Y. Siva Sai Krishna" <sivasaikrishnassk@gmail.com>
License: MIT
License-File: LICENSE
Keywords: container,container-detection,detect,detection,docker,docker-detection,dockerized,environment,inside,is-docker,mit license,process,utilities,utils,ysskrishna
Classifier: Development Status :: 5 - Production/Stable
Classifier: Intended Audience :: Developers
Classifier: License :: OSI Approved :: MIT License
Classifier: Operating System :: POSIX :: Linux
Classifier: Programming Language :: Python :: 3
Classifier: Programming Language :: Python :: 3.8
Classifier: Programming Language :: Python :: 3.9
Classifier: Programming Language :: Python :: 3.10
Classifier: Programming Language :: Python :: 3.11
Classifier: Programming Language :: Python :: 3.12
Classifier: Topic :: Software Development :: Libraries :: Python Modules
Classifier: Topic :: System :: Systems Administration
Classifier: Topic :: Utilities
Classifier: Typing :: Typed
Requires-Python: >=3.8
